influencemapper/__init__.py
influencemapper/author_org/__init__.py
influencemapper/author_org/evaluate.py
influencemapper/author_org/fine_tune.py
influencemapper/author_org/infer.py
influencemapper/author_org/preprocess/gold_eval.py
influencemapper/author_org/preprocess/openai_pred_eval.py
influencemapper/cli.py
influencemapper/postprocess_xml.py
influencemapper/study_org/__init__.py
influencemapper/study_org/evaluate.py
influencemapper/study_org/fine_tune.py
influencemapper/study_org/infer.py
influencemapper/study_org/preprocess/gold_eval.py
influencemapper/study_org/preprocess/openai_pred_eval.py
influencemapper/study_org/process_results.py
influencemapper/util.py
influencemapper-0.9.8.dist-info/LICENSE
influencemapper-0.9.8.dist-info/METADATA
influencemapper-0.9.8.dist-info/WHEEL
influencemapper-0.9.8.dist-info/RECORD
