Metadata-Version: 2.3
Name: influencemapper
Version: 0.9.8
Summary: A tool for extracting information from disclosure statements.
License: MIT
Keywords: disclosure,conflict of interests,competing interest,research
Author: Hardy
Author-email: hardy.oei@gmail.com
Requires-Python: >=3.9,<4.0
Classifier: Development Status :: 4 - Beta
Classifier: Intended Audience :: Developers
Classifier: License :: OSI Approved :: MIT License
Classifier: Natural Language :: English
Classifier: Operating System :: OS Independent
Classifier: Programming Language :: Python :: 3
Classifier: Programming Language :: Python :: 3.9
Classifier: Programming Language :: Python :: 3.10
Classifier: Programming Language :: Python :: 3.11
Classifier: Programming Language :: Python :: 3.12
Classifier: Programming Language :: Python :: 3.13
Classifier: Programming Language :: Python :: Implementation :: CPython
Classifier: Programming Language :: Python :: Implementation :: PyPy
Classifier: Topic :: Scientific/Engineering :: Information Analysis
Requires-Dist: attrs (>=24.2.0,<25.0.0)
Requires-Dist: beautifulsoup4 (>=4.12.3,<5.0.0)
Requires-Dist: fuzzywuzzy (>=0.18.0,<0.19.0)
Requires-Dist: httpx (==0.27.2)
Requires-Dist: lxml (>=5.3.0,<6.0.0)
Requires-Dist: openai (>=1.55.3,<2.0.0)
Requires-Dist: pydantic (>=2.8.2,<3.0.0)
Requires-Dist: python-Levenshtein (>=0.26.1,<0.27.0)
Requires-Dist: tiktoken (>=0.8.0,<0.9.0)
Requires-Dist: tqdm (>=4.66.5,<5.0.0)
Project-URL: Homepage, https://github.com/networkdynamics/influencemapper
